sarthak/__init__.py
sarthak/topsis.py
Topsis_sarthak_101903620-0.0.4.dist-info/LICENCE.md
Topsis_sarthak_101903620-0.0.4.dist-info/METADATA
Topsis_sarthak_101903620-0.0.4.dist-info/WHEEL
Topsis_sarthak_101903620-0.0.4.dist-info/top_level.txt
Topsis_sarthak_101903620-0.0.4.dist-info/RECORD
