Metadata-Version: 2.1
Name: Topsis-sarthak-101903620
Version: 0.0.4
Summary: Topsis
Home-page: UNKNOWN
Author: Sarthak
Author-email: <sarthakbabbar12@gmail.com>
License: UNKNOWN
Keywords: python,Topsis
Platform: UNKNOWN
Classifier: Development Status :: 1 - Planning
Classifier: Intended Audience :: Developers
Classifier: Programming Language :: Python :: 3
Classifier: Operating System :: Unix
Classifier: Operating System :: MacOS :: MacOS X
Classifier: Operating System :: Microsoft :: Windows
License-File: LICENCE.md
